taiwanid/__init__.py
taiwanid/taiwanid.py
TaiwanID-0.2.0.dist-info/LICENSE
TaiwanID-0.2.0.dist-info/METADATA
TaiwanID-0.2.0.dist-info/WHEEL
TaiwanID-0.2.0.dist-info/top_level.txt
TaiwanID-0.2.0.dist-info/RECORD
