Metadata-Version: 2.1
Name: TaiwanID
Version: 0.2.0
Summary: Taiwan ID number tools
Author-email: jhihyulin <jy@jhihyulin.live>
Maintainer-email: jhihyulin <jy@jhihyulin.live>
License:                     GNU GENERAL PUBLIC LICENSE
Project-URL: repository, https://github.com/jhihyulin/TaiwanID.git
Project-URL: issues, https://github.com/jhihyulin/TaiwanID/issues
Keywords: Taiwan,TW,ROC,ID,number,tools
License-File: LICENSE
